topsimp/__init__.py
topsimp/classes.py
topsimp-0.0.1.dist-info/METADATA
topsimp-0.0.1.dist-info/WHEEL
topsimp-0.0.1.dist-info/licenses/LICENSE
topsimp-0.0.1.dist-info/RECORD
